munch/__about__.py
munch/__init__.py
munch/__main__.py
munch/urls.py
munch/wsgi.py
munch/apps/__init__.py
munch/apps/abuse/__init__.py
munch/apps/abuse/admin.py
munch/apps/abuse/apps.py
munch/apps/abuse/contentfilters.py
munch/apps/abuse/forms.py
munch/apps/abuse/models.py
munch/apps/abuse/tests.py
munch/apps/abuse/urls.py
munch/apps/abuse/views.py
munch/apps/abuse/migrations/0001_initial.py
munch/apps/abuse/migrations/0002_auto_20160923_1516.py
munch/apps/abuse/migrations/0003_set_default_for_comments.py
munch/apps/abuse/migrations/0004_auto_20160923_1519.py
munch/apps/abuse/migrations/__init__.py
munch/apps/abuse/templates/abuse/report_abuse.html
munch/apps/abuse/templates/abuse/report_thanks.html
munch/apps/campaigns/__init__.py
munch/apps/campaigns/admin.py
munch/apps/campaigns/apps.py
munch/apps/campaigns/celery.py
munch/apps/campaigns/contentfilters.py
munch/apps/campaigns/exceptions.py
munch/apps/campaigns/fields.py
munch/apps/campaigns/managers.py
munch/apps/campaigns/models.py
munch/apps/campaigns/munchers.py
munch/apps/campaigns/signals.py
munch/apps/campaigns/tasks.py
munch/apps/campaigns/tools.py
munch/apps/campaigns/utils.py
munch/apps/campaigns/validators.py
munch/apps/campaigns/api/__init__.py
munch/apps/campaigns/api/v1/__init__.py
munch/apps/campaigns/api/v1/filters.py
munch/apps/campaigns/api/v1/permissions.py
munch/apps/campaigns/api/v1/serializers.py
munch/apps/campaigns/api/v1/tests.py
munch/apps/campaigns/api/v1/urls.py
munch/apps/campaigns/api/v1/views.py
munch/apps/campaigns/migrations/0001_initial.py
munch/apps/campaigns/migrations/0002_permissions.py
munch/apps/campaigns/migrations/__init__.py
munch/apps/campaigns/templates/campaigns/sending_done_notice_email.txt
munch/apps/campaigns/templates/campaigns/sending_done_notice_email_subject.txt
munch/apps/campaigns/templates/campaigns/sending_notice_email.txt
munch/apps/campaigns/templates/campaigns/sending_notice_email_subject.txt
munch_core-0.1.2.dist-info/DESCRIPTION.rst
munch_core-0.1.2.dist-info/METADATA
munch_core-0.1.2.dist-info/RECORD
munch_core-0.1.2.dist-info/WHEEL
munch_core-0.1.2.dist-info/entry_points.txt
munch_core-0.1.2.dist-info/metadata.json
munch_core-0.1.2.dist-info/top_level.txt
