Metadata-Version: 2.0
Name: munch-core
Version: 0.1.2
Summary: Munch is an emailing platform.
Home-page: https://github.com/crunchmail/munch-core
Author: Crunchmail
Author-email: dev@crunchmail.com
License: GNU AGPLv3
Platform: UNKNOWN
Classifier: Operating System :: OS Independent
Classifier: Programming Language :: Python
Classifier: Programming Language :: Python :: 3
Classifier: Programming Language :: Python :: 3.4
Classifier: Topic :: Internet :: WWW/HTTP
Classifier: Topic :: Internet :: WWW/HTTP :: Dynamic Content
Classifier: License :: OSI Approved :: GNU Affero General Public License v3 or later (AGPLv3+)
Requires-Dist: celery (==3.1.23)
Requires-Dist: chardet (==2.3.0)
Requires-Dist: clamd (==1.0.2)
Requires-Dist: click (==6.6)
Requires-Dist: cssutils (==1.0.1)
Requires-Dist: Django (==1.10.1)
Requires-Dist: django-filter (==0.13.0)
Requires-Dist: django-fsm (==2.4.0)
Requires-Dist: django-humanize (==0.1.2)
Requires-Dist: djangorestframework (==3.4.1)
Requires-Dist: djangorestframework-jwt (==1.8.0)
Requires-Dist: djangorestframework-csv (==1.4.1)
Requires-Dist: djangorestframework-bulk (==0.2.1)
Requires-Dist: dnspython3 (==1.12.0)
Requires-Dist: html2text (==2016.9.19)
Requires-Dist: Jinja2 (==2.8)
Requires-Dist: Markdown (==2.6.6)
Requires-Dist: msgpack-python (==0.4.8)
Requires-Dist: Pillow (==3.3.0)
Requires-Dist: premailer (==3.0.1)
Requires-Dist: Pygments (==2.1.3)
Requires-Dist: python-magic (>=0.4.10)
Requires-Dist: python-slimta (==4.0.0)
Requires-Dist: requests (==2.10.0)
Requires-Dist: django-ipware (==1.1.5)
Requires-Dist: psycopg2 (==2.6.2)
Requires-Dist: psycogreen (==1.0)
Requires-Dist: django-redis (==4.4.4)
Requires-Dist: PyYAML (==3.11)
Requires-Dist: munch-mailsend (==0.1.1)
Provides-Extra: dev
Requires-Dist: bumpversion (==0.5.3); extra == 'dev'
Requires-Dist: docker-compose (==1.8.0); extra == 'dev'
Requires-Dist: mkdocs (==0.16.0); extra == 'dev'
Requires-Dist: mkdocs-bootswatch (==0.4.0); extra == 'dev'
Provides-Extra: tests
Requires-Dist: flake8 (==3.2.0); extra == 'tests'
Requires-Dist: libfaketime (==0.4.2); extra == 'tests'
Requires-Dist: factory-boy (==2.7.0); extra == 'tests'
Requires-Dist: fake-factory (==0.5.10); extra == 'tests'
